balinese_embeddingvector/__init__.py
balinese_embeddingvector/model/Glove.py
balinese_embeddingvector/model/__init__.py
balinese_embeddingvector/pretrained/BaliBERT.py
balinese_embeddingvector/pretrained/BaliFastText.py
balinese_embeddingvector/pretrained/BaliGlove.py
balinese_embeddingvector/pretrained/BaliWord2Vec.py
balinese_embeddingvector/pretrained/BasePretrained.py
balinese_embeddingvector/pretrained/__init__.py
balinese_embeddingvector-0.0.9.dist-info/LICENSE
balinese_embeddingvector-0.0.9.dist-info/METADATA
balinese_embeddingvector-0.0.9.dist-info/WHEEL
balinese_embeddingvector-0.0.9.dist-info/top_level.txt
balinese_embeddingvector-0.0.9.dist-info/RECORD
